Workbook
Name 流動資産_千円: [1]集計00!#REF!
Name 流動資産_千円: [1]集計00!#REF!
Name 流動資産_千円: [1]集計00!#REF!
Name 流動資産_千円: [1]集計00!#REF!

Sheet 表紙
B7: 決 算 報 告 書
B10: （第 25 期）
B11: 自 令和７年１月１日
B12: 自 令和７年12月31日
B22: 株式会社ＦＤＳ
B24: 大阪市中央区徳井町２丁目４番８号

Sheet BS（千円）
B2: 貸 借 対 照 表
B3: (令和７年12月31日 現在)
B4: 株式会社 ＦＤＳ | O4: (単位：千円)
B5: 資産の部 | H5: 負債の部
B6: 科目 | G6: 金額 | H6: 科目 | O6: 金額
C7: 流動資産 | G7: =ROUNDDOWN('BS（円）'!G7/1000,0) -> 48852958 | I7: 流動負債 | O7: =ROUNDDOWN('BS（円）'!O7/1000,0) -> 6462044
E8: 現金及び預金 | G8: =ROUNDDOWN('BS（円）'!G8/1000,0) -> 8666868 | K8: 短期借入金 | O8: =ROUNDDOWN('BS（円）'!O8/1000,0) -> 2951118
E9: 商品 | G9: =ROUNDDOWN('BS（円）'!G9/1000,0) -> 25913063 | K9: １年内償還予定の社債 | O9: =ROUNDDOWN('BS（円）'!O9/1000,0) -> 116000
E10: 仕掛品 | G10: =ROUNDDOWN('BS（円）'!G10/1000,0) -> 8048215 | K10: １年内返済予定の長期借入金 | O10: =ROUNDDOWN('BS（円）'!O10/1000,0) -> 573964
E11: 貯蔵品 | G11: =ROUNDDOWN('BS（円）'!G11/1000,0) -> 6446 | K11: 未払金 | O11: =ROUNDDOWN('BS（円）'!O11/1000,0) -> 111136
E12: 前渡金 | G12: =ROUNDDOWN('BS（円）'!G12/1000,0) -> 334387 | K12: 未払費用 | O12: =ROUNDDOWN('BS（円）'!O12/1000,0) -> 30737
E13: 立替金 | G13: =ROUNDDOWN('BS（円）'!G13/1000,0) -> 5069796 | K13: 未払法人税等 | O13: =ROUNDDOWN('BS（円）'!O13/1000,0) -> 1735158
E14: 前払費用 | G14: =ROUNDDOWN('BS（円）'!G14/1000,0) -> 63786 | K14: 未払消費税等 | O14: =ROUNDDOWN('BS（円）'!O14/1000,0) -> 215534
E15: 短期貸付金 | G15: =ROUNDDOWN('BS（円）'!G16/1000,0) -> 27277 | K15: 前受金 | O15: =ROUNDDOWN('BS（円）'!O15/1000,0) -> 340729
E16: 未収入金 | G16: =ROUNDDOWN('BS（円）'!G17/1000,0) -> 57329 | K16: 前受収益 | O16: =ROUNDDOWN('BS（円）'!O17/1000,0) -> 105
E17: その他 | G17: =ROUNDDOWN(SUM('BS（円）'!G15,'BS（円）'!G18:G20)/1000,0) -> 665788 | K17: その他 | O17: =ROUNDDOWN(SUM('BS（円）'!O16,'BS（円）'!O18,'BS（円）'!O19)/1000,0) -> 387560
C18: 固定資産 | G18: =ROUNDDOWN('BS（円）'!G22/1000,0) -> 16955493 | I18: 固定負債 | O18: =ROUNDDOWN('BS（円）'!O22/1000,0) -> 45367479
D19: 有形固定資産 | G19: =ROUNDDOWN('BS（円）'!G23/1000,0) -> 16638722 | K19: 社債 | O19: =ROUNDDOWN('BS（円）'!O24/1000,0) -> 830000
E20: 建物 | G20: =ROUNDDOWN('BS（円）'!G24/1000,0) -> 3718243 | K20: 長期借入金 | O20: =ROUNDDOWN('BS（円）'!O23/1000,0) -> 44537479
E21: 建物附属設備 | G21: =ROUNDDOWN('BS（円）'!G25/1000,0) -> 1927012 | H21: 負債合計 | O21: =ROUNDDOWN('BS（円）'!O31/1000,0) -> 51829524
E22: 構築物 | G22: =ROUNDDOWN('BS（円）'!G26/1000,0) -> 9668 | H22: 純資産の部
E23: 車両運搬具 | G23: =ROUNDDOWN('BS（円）'!G27/1000,0) -> 8671 | I23: 株主資本 | O23: =SUM(O24,O25) -> 13978928
E24: 工具器具備品 | G24: =ROUNDDOWN(('BS（円）'!G28+'BS（円）'!G29)/1000,0) -> 31985 | K24: 資本金 | O24: =ROUNDDOWN('BS（円）'!O34/1000,0) -> 99000
E25: 土地 | G25: =ROUNDDOWN('BS（円）'!G30/1000,0) -> 10943139 | K25: 利益剰余金 | O25: =O26+O27 -> 13879928
D26: 無形固定資産 | G26: =ROUNDDOWN('BS（円）'!G32/1000,0) -> 8136 | L26: 利益準備金 | O26: =ROUNDDOWN('BS（円）'!O36/1000,0) -> 24750
E27: ソフトウェア | G27: =ROUNDDOWN('BS（円）'!G34/1000,0) -> 8101 | L27: その他利益剰余金 | O27: =ROUNDDOWN('BS（円）'!O37/1000,0) -> 13855178
E28: 電話加入権 | G28: =ROUNDDOWN('BS（円）'!G33/1000,0) -> 35 | M28: 繰越利益剰余金 | O28: =ROUNDDOWN('BS（円）'!O38/1000,0) -> 13855178
D29: 投資その他の資産 | G29: =ROUNDDOWN('BS（円）'!G35/1000,0) -> 308634
E30: 投資有価証券 | G30: =ROUNDDOWN('BS（円）'!G36/1000,0) -> 150570
E31: 出資金 | G31: =ROUNDDOWN('BS（円）'!G37/1000,0) -> 20370
E32: 差入保証金 | G32: =ROUNDDOWN('BS（円）'!G38/1000,0) -> 80517
E33: 長期前払費用 | G33: =ROUNDDOWN('BS（円）'!G39/1000,0) -> 42626
E34: その他 | G34: =ROUNDDOWN('BS（円）'!G40/1000,0) -> 14550 | H34: 純資産合計 | O34: =ROUNDDOWN('BS（円）'!O40/1000,0) -> 13978928
B35: 資産合計 | G35: =ROUNDDOWN('BS（円）'!G41/1000,0) -> 65808452 | H35: 負債・純資産合計 | O35: =ROUNDDOWN('BS（円）'!O41/1000,0) -> 65808452

Sheet PL（千円）
B2: 損 益 計 算 書
B3: (自 令和７年１月１日 至 令和７年12月31日)
B4: 株式会社 ＦＤＳ | H4: (単位：千円)
B5: 科目 | G5: 金額
C6: 売上高 | H6: =ROUNDDOWN('PL（円）'!H6/1000,0) -> 40055628
C7: 売上原価
D8: 期首商品棚卸高 | G8: =ROUNDDOWN('PL（円）'!G8/1000,0) -> 21923271
D9: 当期商品仕入高 | G9: =ROUNDDOWN('PL（円）'!G9/1000,0) -> 34917470
D10: 合計 | G10: =ROUNDDOWN('PL（円）'!G10/1000,0) -> 56840742
D11: 他勘定振替高 | G11: =ROUNDDOWN('PL（円）'!G11/1000,0) -> 755356
D12: 期末商品棚卸高 | G12: =ROUNDDOWN('PL（円）'!G12/1000,0) -> 25913063 | H12: =ROUNDDOWN('PL（円）'!H12/1000,0) -> 30172322
D13: 売上総利益 | H13: =ROUNDDOWN('PL（円）'!H13/1000,0) -> 9883305
C14: 販売費及び一般管理費 | H14: =ROUNDDOWN('PL（円）'!H14/1000,0) -> 4125941
D15: 営業利益 | H15: =ROUNDDOWN('PL（円）'!H15/1000,0) -> 5757364
C16: 営業外収益
D17: 受取利息 | G17: =ROUNDDOWN('PL（円）'!G17/1000,0) -> 12205
D18: 受取配当金 | G18: =ROUNDDOWN('PL（円）'!G18/1000,0) -> 295
D19: 雑収入 | G19: =ROUNDDOWN('PL（円）'!G19/1000,0) -> 35202 | H19: =ROUNDDOWN('PL（円）'!H19/1000,0) -> 47702
C20: 営業外費用
D21: 支払利息 | G21: =ROUNDDOWN('PL（円）'!G21/1000,0) -> 777443 | H21: =ROUNDDOWN('PL（円）'!H21/1000,0) -> 777443
D22: 経常利益 | H22: =ROUNDDOWN('PL（円）'!H22/1000,0) -> 5027622
C23: 特別利益
D24: 固定資産売却益 | G24: =ROUNDDOWN('PL（円）'!#REF!/1000,0) -> #REF! | H24: =ROUNDDOWN('PL（円）'!#REF!/1000,0) -> #REF!
C25: 特別損失
D26: その他 | G26: =ROUNDDOWN('PL（円）'!G24/1000,0) -> 29310 | H26: =ROUNDDOWN('PL（円）'!H24/1000,0) -> 29310
D27: 税引前当期純利益 | H27: =ROUNDDOWN('PL（円）'!H25/1000,0) -> 4998312
B28: 法人税、住民税及び事業税 | D28: 法人税、住民税及び事業税 | H28: =ROUNDDOWN('PL（円）'!G26/1000,0) -> 1747587
B29: 法人税、住民税及び事業税 | D29: 法人税等調整額 | G29: =ROUNDDOWN('PL（円）'!G27/1000,0) -> 0 | H29: =ROUNDDOWN('PL（円）'!H27/1000,0) -> 1747587
D30: 当期純利益 | H30: =ROUNDDOWN('PL（円）'!H28/1000,0) -> 3250725

Sheet SS（千円）横型
B2: 株主資本等変動計算書
B3: (自 令和７年１月１日 至 令和７年12月31日)
C4: 株式会社 ＦＤＳ | J4: (単位：千円)
E5: 株主資本 | J5: 純資産 合計
E6: 資本金 | F6: 利益剰余金 | I6: 株主資本 合計
F7: 利益準備金 | G7: その他 利益剰余金 | H7: 利益剰余金 合計
G8: 繰越 利益剰余金
C9: 当期首残高 | E9: =ROUNDDOWN('SS（円）横型'!E10/1000,0) -> 99000 | F9: =ROUNDDOWN('SS（円）横型'!F10/1000,0) -> 24750 | G9: =ROUNDDOWN('SS（円）横型'!G10/1000,0) -> 11901432 | H9: =ROUNDDOWN('SS（円）横型'!H10/1000,0) -> 11926182 | I9: =ROUNDDOWN('SS（円）横型'!I10/1000,0) -> 12025182 | J9: =ROUNDDOWN('SS（円）横型'!J10/1000,0) -> 12025182
C10: 当期変動額
D11: ='SS（円）横型'!D12 -> 当期純利益 | E11: =ROUNDDOWN('SS（円）横型'!E12/1000,0) -> 0 | F11: =ROUNDDOWN('SS（円）横型'!F12/1000,0) -> 0 | G11: =ROUNDDOWN('SS（円）横型'!G12/1000,0) -> 3250725 | H11: =ROUNDDOWN('SS（円）横型'!H12/1000,0) -> 3250725 | I11: =ROUNDDOWN('SS（円）横型'!I12/1000,0) -> 3250725 | J11: =ROUNDDOWN('SS（円）横型'!J12/1000,0) -> 3250725
D12: ='SS（円）横型'!D13 -> 剰余金の配当 | E12: =ROUNDDOWN('SS（円）横型'!E13/1000,0) -> 0 | F12: =ROUNDDOWN('SS（円）横型'!F13/1000,0) -> 0 | G12: =ROUNDDOWN('SS（円）横型'!G13/1000,0) -> -1296980 | H12: =ROUNDDOWN('SS（円）横型'!H13/1000,0) -> -1296980 | I12: =ROUNDDOWN('SS（円）横型'!I13/1000,0) -> -1296980 | J12: =ROUNDDOWN('SS（円）横型'!J13/1000,0) -> -1296980
C13: 当期変動額合計 | E13: =ROUNDDOWN('SS（円）横型'!E14/1000,0) -> 0 | F13: =ROUNDDOWN('SS（円）横型'!F14/1000,0) -> 0 | G13: =ROUNDDOWN('SS（円）横型'!G14/1000,0) -> 1953745 | H13: =ROUNDDOWN('SS（円）横型'!H14/1000,0) -> 1953745 | I13: =ROUNDDOWN('SS（円）横型'!I14/1000,0) -> 1953745 | J13: =ROUNDDOWN('SS（円）横型'!J14/1000,0) -> 1953745
C14: 当期末残高 | E14: =ROUNDDOWN('SS（円）横型'!E15/1000,0) -> 99000 | F14: =ROUNDDOWN('SS（円）横型'!F15/1000,0) -> 24750 | G14: =ROUNDDOWN('SS（円）横型'!G15/1000,0) -> 13855178 | H14: =ROUNDDOWN('SS（円）横型'!H15/1000,0) -> 13879928 | I14: =ROUNDDOWN('SS（円）横型'!I15/1000,0) -> 13978928 | J14: =ROUNDDOWN('SS（円）横型'!J15/1000,0) -> 13978928

Sheet BS（円）
B2: 貸 借 対 照 表
B3: ='BS（千円）'!B3 -> (令和７年12月31日 現在)
B4: 株式会社 ＦＤＳ | O4: (単位：円)
B5: 科目 | G5: 金額 | H5: 科目 | O5: 金額
B6: (資産の部) | H6: (負債の部)
C7: 流動資産 | G7: =SUM(G8:G21) -> 48852958853 | I7: 流動負債 | O7: =SUM(O8:O20) -> 6462044613 | Q7: 確認状調書参照
E8: 現金及び預金 | G8: =8817438780-G36 -> 8666868080 | K8: 短期借入金 | O8: =Q8 -> 2951118486 | Q8: 2951118486 | R8: 561586486
E9: 商品 | G9: 25913063482 | K9: １年内償還予定の社債 | O9: =Q9 -> 116000000 | Q9: 116000000
E10: 商品建築中 | G10: 8048215000 | K10: １年内返済予定の 長期借入金 | O10: =Q10 -> 573964723 | Q10: 573964723
E11: 貯蔵品 | G11: 6446800 | K11: 未払金 | O11: 111136041
E12: 前渡金 | G12: 334387470 | K12: 未払費用 | O12: 30737582
E13: 立替金 | G13: 5069796261 | K13: 未払法人税等 | O13: 1735158800
E14: 前払費用 | G14: 63786053 | K14: 未払消費税等 | O14: 215534100
E15: 未収収益 | G15: 227329 | K15: 前受金 | O15: 340729120
E16: 短期貸付金 | G16: 27277180 | K16: 預り金 | O16: 13081845
E17: 未収入金 | G17: 57329760 | K17: 前受収益 | O17: 105000
E18: 仮払金 | G18: 20478991 | K18: 仮受金 | O18: 60699108
E19: 預け金 | G19: 5279970 | K19: 預り保証金 | O19: 313779808
E20: 仮払税金(売買関連) | G20: 639802477
C22: 固定資産 | G22: =SUM(G23,G32,G35) -> 16955493415 | I22: 固定負債 | O22: =SUM(O23:O28) -> 45367479392
D23: 有形固定資産 | G23: =SUM(G24:G31) -> 16638722122 | K23: 長期借入金 | O23: =Q23 -> 44537479392 | Q23: 44537479392 | R23: 47500976115
E24: 建物 | G24: 3718243907 | K24: 社債 | O24: =Q24 -> 830000000 | Q24: 830000000 | R24: 946000000
E25: 附属設備 | G25: 1927012939
E26: 構築物 | G26: 9668261 | Q26: =SUM(Q8:Q24) -> 49008562601 | R26: =SUM(R8:R24) -> 49008562601 | S26: =R26-Q26 -> 0
E27: 車両運搬具 | G27: 8671873
E28: 工具器具備品 | G28: 26920475
E29: 一括償却資産 | G29: 5065204
E30: 土地 | G30: 10943139463
H31: 負債合計 | O31: =O7+O22 -> 51829524005
D32: 無形固定資産 | G32: =SUM(G33:G34) -> 8136563 | H32: (純資産の部)
E33: 電話加入権 | G33: 35000 | I33: 株主資本 | O33: =SUM(O34,O35) -> 13978928263
E34: ソフトウェア | G34: 8101563 | K34: 資本金 | O34: 99000000
D35: 投資その他の資産 | G35: =SUM(G36:G40) -> 308634730 | K35: 利益剰余金 | O35: =O36+O37 -> 13879928263
E36: 投資有価証券 | G36: 150570700 | L36: 利益準備金 | O36: 24750000
E37: 出資金 | G37: 20370000 | L37: その他利益剰余金 | O37: =O38 -> 13855178263
E38: 差入保証金 | G38: 80517670 | M38: 繰越利益剰余金 | O38: 13855178263
E39: 長期前払費用 | G39: 42626360
E40: 入会金 | G40: 14550000 | H40: 純資産合計 | O40: =SUM(O33) -> 13978928263
B41: 資産合計 | G41: =SUM(G7,G22,) -> 65808452268 | H41: 負債・純資産合計 | O41: =O31+O40 -> 65808452268

Sheet PL（円）
B2: 損 益 計 算 書
B3: ='PL（円）銀行説明用'!B3 -> (自 令和７年１月１日 至 令和７年12月31日)
B4: 株式会社 ＦＤＳ | H4: (単位：円)
B5: 科目 | G5: 金額
C6: 売上高 | H6: 40055628529
C7: 売上原価
D8: 期首商品棚卸高 | G8: 21923271769
D9: 当期商品仕入高 | G9: 34917470820
D10: 合計 | G10: =SUM(G8:G9) -> 56840742589
D11: 他勘定振替高 | G11: 755356361
D12: 期末商品棚卸高 | G12: 25913063482 | H12: =G10-G11-G12 -> 30172322746
D13: 売上総利益 | H13: =+H6-H12 -> 9883305783
C14: 販売費及び一般管理費 | H14: 4125941769
D15: 営業利益 | H15: =+H13-H14 -> 5757364014
C16: 営業外収益
D17: 受取利息 | G17: 12205025
D18: 受取配当金 | G18: 295342
D19: 雑収入 | G19: 35202381 | H19: =SUM(G17:G19) -> 47702748
C20: 営業外費用
D21: 支払利息 | G21: 777443792 | H21: =SUM(G21:G21) -> 777443792
D22: 経常利益 | H22: =H15+H19-H21 -> 5027622970
C23: 特別損失
D24: その他 | G24: 29310596 | H24: =SUM(G24:G24) -> 29310596
D25: 税引前当期純利益 | H25: =H22-H24 -> 4998312374
B26: 法人税、住民税及び事業税 | D26: 法人税、住民税及び事業税 | G26: 1747587084
B27: 法人税、住民税及び事業税 | D27: 法人税等調整額 | G27: 0 | H27: =SUM(G26:G27) -> 1747587084
D28: 当期純利益 | H28: =+H25-H27 -> 3250725290

Sheet SS（円）横型
B2: 株主資本等変動計算書
B3: (自 令和７年１月１日 至 令和７年12月31日)
B4: 株式会社 ＦＤＳ | J4: (単位：円)
E6: 株主資本 | J6: 純資産合計
E7: 資本金 | F7: 利益剰余金 | I7: 株主資本 合計
F8: 利益準備金 | G8: その他 利益剰余金 | H8: 利益剰余金 合計
G9: 繰越 利益剰余金
C10: 当期首残高 | E10: =J19 -> 99000000 | F10: =J22 -> 24750000 | G10: =J25 -> 11901432973 | H10: =F10+G10 -> 11926182973 | I10: =E10+H10 -> 12025182973 | J10: =I10 -> 12025182973
C11: 当期変動額
D12: 当期純利益 | E12: 0 | F12: 0 | G12: ='PL（円）'!H28 -> 3250725290 | H12: =F12+G12 -> 3250725290 | I12: =E12+H12 -> 3250725290 | J12: =I12 -> 3250725290
D13: 剰余金の配当 | E13: 0 | F13: 0 | G13: -1296980000 | H13: =F13+G13 -> -1296980000 | I13: =E13+H13 -> -1296980000 | J13: =I13 -> -1296980000
C14: 当期変動額合計 | E14: =SUM(E12:E13) -> 0 | F14: =SUM(F12:F13) -> 0 | G14: =SUM(G12:G13) -> 1953745290 | H14: =SUM(H12:H13) -> 1953745290 | I14: =SUM(I12:I13) -> 1953745290 | J14: =SUM(J12:J13) -> 1953745290
C15: 当期末残高 | E15: =E10+E14 -> 99000000 | F15: =F10+F14 -> 24750000 | G15: =G10+G14 -> 13855178263 | H15: =H10+H14 -> 13879928263 | I15: =I10+I14 -> 13978928263 | J15: =J10+J14 -> 13978928263
C18: （株主資本）
D19: 資本金 | G19: 当期首残高 | J19: 99000000
G20: 当期末残高 | J20: =SUM(J19:J19) -> 99000000
D21: 利益剰余金
D22: 利益準備金 | G22: 当期首残高 | J22: 24750000
G23: 当期末残高 | J23: =SUM(J22:J22) -> 24750000
D24: その他利益剰余金
D25: 繰越利益剰余金 | G25: 当期首残高 | J25: 11901432973
G26: 当期変動額 当期純利益金額 | J26: ='PL（円）'!H28 -> 3250725290
G27: 当期変動額 剰余金の配当 | J27: -1296980000
G28: 当期末残高 | J28: =SUM(J25:J27) -> 13855178263
D29: 利益剰余金合計 | G29: 当期首残高 | J29: =J22+J25 -> 11926182973
G30: 当期変動額 | J30: =SUM(J26:J27) -> 1953745290
G31: 当期末残高 | J31: =SUM(J29:J30) -> 13879928263
D32: 株主資本合計 | G32: 当期首残高 | J32: =J19+J29 -> 12025182973
G33: 当期変動額 | J33: =J30 -> 1953745290
G34: 当期末残高 | J34: =J32+J33 -> 13978928263
C35: 純資産の部合計 | G35: 当期首残高 | J35: =J32 -> 12025182973
G36: 当期変動額 | J36: =J33 -> 1953745290
G37: 当期末残高 | J37: =J35+J36 -> 13978928263

Sheet 期中平均株式数
A1: 期中平均株式数（月数換算）
A2: 45627 | B2: 1980 | C2: 株
A3: 45658 | B3: 1980 | C3: 株
A4: 45689 | B4: 1980 | C4: 株
A5: 45717 | B5: 1980 | C5: 株
A6: 45748 | B6: 1980 | C6: 株
A7: 45778 | B7: 1980 | C7: 株
A8: 45809 | B8: 1980 | C8: 株
A9: 45839 | B9: 1980 | C9: 株
A10: 45870 | B10: 1980 | C10: 株
A11: 45901 | B11: 1980 | C11: 株
A12: 45931 | B12: 1980 | C12: 株
A13: 45962 | B13: 1980 | C13: 株
A14: 45992 | B14: 1980 | C14: 株
A15: 期中平均 | B15: =AVERAGE(B3:B14) -> 1980 | C15: 株
A17: 1株当たり純資産 | B17: ='BS（円）'!O40/((B2+B14)/2) -> 7060064.8
A18: 1株当たり純利益 | B18: ='PL（円）'!H28/期中平均株式数!B15 -> 1641780.4

Sheet BS（円）銀行説明用
B2: 貸 借 対 照 表
B3: ='BS（千円）'!B3 -> (令和７年12月31日 現在)
B4: 株式会社 ＦＤＳ | O4: (単位：円)
B5: 資産の部 | H5: 負債の部
B6: 科目 | G6: 金額 | H6: 科目 | O6: 金額
C7: 流動資産 | G7: =ROUNDDOWN('BS（円）'!G7/1,0) -> 48852958853 | I7: 流動負債 | O7: =ROUNDDOWN('BS（円）'!O7/1,0) -> 6462044613
E8: 現金及び預金 | G8: =ROUNDDOWN('BS（円）'!G8/1,0) -> 8666868080 | K8: 短期借入金 | O8: =ROUNDDOWN('BS（円）'!O8/1,0) -> 2951118486
E9: 商品 | G9: =ROUNDDOWN('BS（円）'!G9/1,0) -> 25913063482 | K9: １年内償還予定の社債 | O9: =ROUNDDOWN('BS（円）'!O9/1,0) -> 116000000
E10: 仕掛品（商品） | G10: =ROUNDDOWN('BS（円）'!G10/1,0) -> 8048215000 | K10: １年内返済予定の長期借入金 | O10: =ROUNDDOWN('BS（円）'!O10/1,0) -> 573964723
E11: 貯蔵品 | G11: =ROUNDDOWN('BS（円）'!G11/1,0) -> 6446800 | K11: 未払金 | O11: =ROUNDDOWN('BS（円）'!O11/1,0) -> 111136041
E12: 前渡金 | G12: =ROUNDDOWN('BS（円）'!G12/1,0) -> 334387470 | K12: 未払費用 | O12: =ROUNDDOWN('BS（円）'!O12/1,0) -> 30737582
E13: 立替金 | G13: =ROUNDDOWN('BS（円）'!G13/1,0) -> 5069796261 | K13: 未払法人税等 | O13: =ROUNDDOWN('BS（円）'!O13/1,0) -> 1735158800
E14: 前払費用 | G14: =ROUNDDOWN('BS（円）'!G14/1,0) -> 63786053 | K14: 未払消費税等 | O14: =ROUNDDOWN('BS（円）'!O14/1,0) -> 215534100
E15: 短期貸付金 | G15: =ROUNDDOWN('BS（円）'!G16/1,0) -> 27277180 | K15: 前受金 | O15: =ROUNDDOWN('BS（円）'!O15/1,0) -> 340729120
E16: 未収入金 | G16: =ROUNDDOWN('BS（円）'!G17/1,0) -> 57329760 | K16: 預り金 | O16: =ROUNDDOWN('BS（円）'!O16/1,0) -> 13081845
E17: その他（未収収益） | G17: =ROUNDDOWN(SUM('BS（円）'!G15)/1,0) -> 227329 | K17: 前受収益 | O17: =ROUNDDOWN('BS（円）'!O17/1,0) -> 105000
E18: その他（仮払金） | G18: =ROUNDDOWN(SUM('BS（円）'!G18)/1,0) -> 20478991 | K18: 仮受金 | O18: =ROUNDDOWN('BS（円）'!O18/1,0) -> 60699108
E19: その他（預け金） | G19: =ROUNDDOWN(SUM('BS（円）'!G19)/1,0) -> 5279970 | K19: 預り保証金 | O19: =ROUNDDOWN('BS（円）'!O19/1,0) -> 313779808
E20: その他（仮払税金） | G20: =ROUNDDOWN(SUM('BS（円）'!G20)/1,0) -> 639802477
C22: 固定資産 | G22: =ROUNDDOWN('BS（円）'!G22/1,0) -> 16955493415 | I22: 固定負債 | O22: =ROUNDDOWN('BS（円）'!O22/1,0) -> 45367479392
D23: 有形固定資産 | G23: =ROUNDDOWN('BS（円）'!G23/1,0) -> 16638722122 | K23: 社債 | O23: =ROUNDDOWN('BS（円）'!O23/1,0) -> 44537479392
E24: 建物 | G24: =ROUNDDOWN('BS（円）'!G24/1,0) -> 3718243907 | K24: 長期借入金 | O24: =ROUNDDOWN('BS（円）'!O24/1,0) -> 830000000
E25: 建物附属設備 | G25: =ROUNDDOWN('BS（円）'!G25/1,0) -> 1927012939 | H25: 負債合計 | O25: =ROUNDDOWN('BS（円）'!O31/1,0) -> 51829524005
E26: 構築物 | G26: =ROUNDDOWN('BS（円）'!G26/1,0) -> 9668261 | H26: 純資産の部
E27: 車両運搬具 | G27: =ROUNDDOWN('BS（円）'!G27/1,0) -> 8671873 | I27: 株主資本 | O27: =SUM(O28,O29) -> 13978928263
E28: 工具器具備品（及び一括償却資産） | G28: =ROUNDDOWN(('BS（円）'!G28+'BS（円）'!G29)/1,0) -> 31985679 | K28: 資本金 | O28: =ROUNDDOWN('BS（円）'!O34/1,0) -> 99000000
E29: 土地 | G29: =ROUNDDOWN('BS（円）'!G30/1,0) -> 10943139463 | K29: 利益剰余金 | O29: =O30+O31 -> 13879928263
D30: 無形固定資産 | G30: =ROUNDDOWN('BS（円）'!G32/1,0) -> 8136563 | L30: 利益準備金 | O30: =ROUNDDOWN('BS（円）'!O36/1,0) -> 24750000
E31: ソフトウェア | G31: =ROUNDDOWN('BS（円）'!G34/1,0) -> 8101563 | L31: その他利益剰余金 | O31: =ROUNDDOWN('BS（円）'!O37/1,0) -> 13855178263
E32: 電話加入権 | G32: =ROUNDDOWN('BS（円）'!G33/1,0) -> 35000 | M32: 繰越利益剰余金 | O32: =ROUNDDOWN('BS（円）'!O38/1,0) -> 13855178263
D33: 投資その他の資産 | G33: =ROUNDDOWN('BS（円）'!G35/1,0) -> 308634730
E34: 投資有価証券 | G34: =ROUNDDOWN('BS（円）'!G36/1,0) -> 150570700
E35: 出資金 | G35: =ROUNDDOWN('BS（円）'!G37/1,0) -> 20370000
E36: 差入保証金 | G36: =ROUNDDOWN('BS（円）'!G38/1,0) -> 80517670
E37: 長期前払費用 | G37: =ROUNDDOWN('BS（円）'!G39/1,0) -> 42626360
E38: その他（入会金） | G38: =ROUNDDOWN('BS（円）'!G40/1,0) -> 14550000 | H38: 純資産合計 | O38: =ROUNDDOWN('BS（円）'!O40/1,0) -> 13978928263
B39: 資産合計 | G39: =ROUNDDOWN('BS（円）'!G41/1,0) -> 65808452268 | H39: 負債・純資産合計 | O39: =ROUNDDOWN('BS（円）'!O41/1,0) -> 65808452268

Sheet PL（円）銀行説明用
B2: 損 益 計 算 書
B3: ='PL（千円）'!B3 -> (自 令和７年１月１日 至 令和７年12月31日)
B4: 株式会社 ＦＤＳ | H4: (単位：千円)
B5: 科目 | G5: 金額
C6: 売上高 | H6: =ROUNDDOWN('PL（円）'!H6/1,0) -> 40055628529
C7: 売上原価
D8: 期首商品棚卸高 | G8: =ROUNDDOWN('PL（円）'!G8/1,0) -> 21923271769
D9: 当期商品仕入高 | G9: =ROUNDDOWN('PL（円）'!G9/1,0) -> 34917470820
D10: 合計 | G10: =ROUNDDOWN('PL（円）'!G10/1,0) -> 56840742589
D11: 他勘定振替高 | G11: =ROUNDDOWN('PL（円）'!G11/1,0) -> 755356361
D12: 期末商品棚卸高 | G12: =ROUNDDOWN('PL（円）'!G12/1,0) -> 25913063482 | H12: =ROUNDDOWN('PL（円）'!H12/1,0) -> 30172322746
D13: 売上総利益 | H13: =ROUNDDOWN('PL（円）'!H13/1,0) -> 9883305783
C14: 販売費及び一般管理費 | H14: =ROUNDDOWN('PL（円）'!H14/1,0) -> 4125941769
D15: 営業利益 | H15: =ROUNDDOWN('PL（円）'!H15/1,0) -> 5757364014
C16: 営業外収益
D17: 受取利息 | G17: =ROUNDDOWN('PL（円）'!G17/1,0) -> 12205025
D18: 受取配当金 | G18: =ROUNDDOWN('PL（円）'!G18/1,0) -> 295342
D19: 雑収入 | G19: =ROUNDDOWN('PL（円）'!G19/1,0) -> 35202381 | H19: =ROUNDDOWN('PL（円）'!H19/1,0) -> 47702748
C20: 営業外費用
D21: 支払利息 | G21: =ROUNDDOWN('PL（円）'!G21/1,0) -> 777443792 | H21: =ROUNDDOWN('PL（円）'!H21/1,0) -> 777443792
D22: 経常利益 | H22: =ROUNDDOWN('PL（円）'!H22/1,0) -> 5027622970
C23: 特別利益
D24: 固定資産売却益 | G24: =ROUNDDOWN('PL（円）'!#REF!/1,0) -> #REF! | H24: =ROUNDDOWN('PL（円）'!#REF!/1,0) -> #REF!
C25: 特別損失
D26: その他（特別損失） | G26: =ROUNDDOWN('PL（円）'!G24/1,0) -> 29310596 | H26: =ROUNDDOWN('PL（円）'!H24/1,0) -> 29310596
D27: 税引前当期純利益 | H27: =ROUNDDOWN('PL（円）'!H25/1,0) -> 4998312374
B28: 法人税、住民税及び事業税 | D28: 法人税、住民税及び事業税 | H28: =ROUNDDOWN('PL（円）'!G26/1,0) -> 1747587084
B29: 法人税、住民税及び事業税 | D29: 法人税等調整額 | G29: =ROUNDDOWN('PL（円）'!G27/1,0) -> 0 | H29: =ROUNDDOWN('PL（円）'!H27/1,0) -> 1747587084
D30: 当期純利益 | H30: =ROUNDDOWN('PL（円）'!H28/1,0) -> 3250725290

Sheet SS（千円）
B2: 株主資本等変動計算書
B3: (自 令和７年１月１日 至 令和７年12月31日)
B4: 株式会社 ＦＤＳ | I4: (単位：千円)
C6: （株主資本）
D7: 資本金 | G7: 当期首残高 | I7: =ROUNDDOWN('SS（円）'!I7/1000,0) -> 99000
G8: 当期末残高 | I8: =ROUNDDOWN('SS（円）'!I8/1000,0) -> 99000
D9: 利益剰余金
D10: 利益準備金 | G10: 当期首残高 | I10: =ROUNDDOWN('SS（円）'!I10/1000,0) -> 24750
G11: 当期末残高 | I11: =ROUNDDOWN('SS（円）'!I11/1000,0) -> 24750
D12: その他利益剰余金
D13: 繰越利益剰余金 | G13: 当期首残高 | I13: =ROUNDDOWN('SS（円）'!I13/1000,0) -> 11901432
G14: 当期変動額 当期純利益 | I14: =ROUNDDOWN('SS（円）'!I14/1000,0) -> 3250725
G15: 剰余金の配当 | I15: =ROUNDDOWN('SS（円）'!I15/1000,0) -> -1296980
G16: 当期末残高 | I16: =ROUNDDOWN('SS（円）'!I16/1000,0) -> 13855178
D17: 利益剰余金合計 | G17: 当期首残高 | I17: =ROUNDDOWN('SS（円）'!I17/1000,0) -> 11926182
G18: 当期変動額 当期純利益 | I18: =ROUNDDOWN('SS（円）'!I18/1000,0) -> 1953745
G19: 当期末残高 | I19: =ROUNDDOWN('SS（円）'!I19/1000,0) -> 13879928
D20: 株主資本合計 | G20: 当期首残高 | I20: =ROUNDDOWN('SS（円）'!I20/1000,0) -> 12025182
G21: 当期変動額 | I21: =ROUNDDOWN('SS（円）'!I21/1000,0) -> 1953745
G22: 当期末残高 | I22: =ROUNDDOWN('SS（円）'!I22/1000,0) -> 13978928
C23: 純資産の部合計 | G23: 当期首残高 | I23: =ROUNDDOWN('SS（円）'!I23/1000,0) -> 12025182
G24: 当期変動額 | I24: =ROUNDDOWN('SS（円）'!I24/1000,0) -> 1953745
G25: 当期末残高 | I25: =ROUNDDOWN('SS（円）'!I25/1000,0) -> 13978928

Sheet SS（円）
B2: 株主資本等変動計算書
B3: ='SS（千円）'!B3 -> (自 令和７年１月１日 至 令和７年12月31日)
B4: 株式会社 ＦＤＳ | I4: (単位：円)
C6: （株主資本）
D7: 資本金 | G7: 当期首残高 | I7: 99000000
G8: 当期末残高 | I8: =SUM(I7:I7) -> 99000000
D9: 利益剰余金
D10: 利益準備金 | G10: 当期首残高 | I10: ='SS（円）横型'!F10 -> 24750000
G11: 当期末残高 | I11: =SUM(I10:I10) -> 24750000
D12: その他利益剰余金
D13: 繰越利益剰余金 | G13: 当期首残高 | I13: ='SS（円）横型'!G10 -> 11901432973
G14: 当期変動額 当期純利益金額 | I14: ='PL（円）'!H28 -> 3250725290
G15: 剰余金の配当 | I15: ='SS（円）横型'!G13 -> -1296980000
G16: 当期末残高 | I16: =SUM(I13:I15) -> 13855178263
D17: 利益剰余金合計 | G17: 当期首残高 | I17: =I10+I13 -> 11926182973
G18: 当期変動額 当期純利益金額 | I18: ='SS（円）横型'!H14 -> 1953745290
G19: 当期末残高 | I19: =SUM(I17:I18) -> 13879928263
D20: 株主資本合計 | G20: 当期首残高 | I20: =I7+I17 -> 12025182973
G21: 当期変動額 | I21: =I18 -> 1953745290
G22: 当期末残高 | I22: =I20+I21 -> 13978928263
C23: 純資産の部合計 | G23: 当期首残高 | I23: =I20 -> 12025182973
G24: 当期変動額 | I24: =I21 -> 1953745290
G25: 当期末残高 | I25: =I23+I24 -> 13978928263
